pytest_influx/__init__.py
pytest_influx/db_cleaner.py
pytest_influx-0.1.0.dist-info/LICENSE
pytest_influx-0.1.0.dist-info/METADATA
pytest_influx-0.1.0.dist-info/WHEEL
pytest_influx-0.1.0.dist-info/RECORD
