Metadata-Version: 2.1
Name: pytest-influx
Version: 0.1.0
Summary: Pytest plugin for managing your influx instance between test runs
Author: vonum
Author-email: vonum.mk@gmail.com
Requires-Python: >=3.11,<4.0
Classifier: Programming Language :: Python :: 3
Classifier: Programming Language :: Python :: 3.11
Requires-Dist: influxdb-client (>=1.46.0,<2.0.0)
Requires-Dist: pytest (>=8.3.3,<9.0.0)
